[
    {
        "id": "ERC20broken_contract_context",
        "chunk_type": "CONTRACT_CONTEXT",
        "source_contract": "ERC20broken.sol",
        "target_function": "ALL",
        "text_chunk": "// SPDX-License-Identifier: MIT\n// OpenZeppelin Contracts v4.4.1 (token/ERC20/ERC20.sol)\n\npragma solidity ^0.8.0;\n\nimport \"../ContractsAndProperties/IERC20.sol\";\nimport \"../ContractsAndProperties/IERC20Metadata.sol\";\n\ncontract ERC20 is IERC20, IERC20Metadata {\n    mapping(address => uint256) private _balances;\n\n    mapping(address => mapping(address => uint256)) private _allowances;\n\n    uint256 private _totalSupply;\n\n    address public _owner;\n\n    constructor() {\n    }\n\n    modifier onlyOwner() {\n        require(_owner == msg.sender);\n        _;\n    }\n\n    function name() public view virtual override returns (string memory) {\n        return \"\";\n    }\n\n    function symbol() public view virtual override returns (string memory) {\n        return \"\";\n    }\n\n    function decimals() public view virtual override returns (uint8) {\n        return 18;\n    }\n    function totalSupply() public view virtual override returns (uint256) {\n        return _totalSupply;\n    }\n    function balanceOf(address account)\n        public\n        view\n        virtual\n        override\n        returns (uint256)\n    {\n        return _balances[account];\n    }\n    function transfer(address recipient, uint256 amount)\n        public\n        virtual\n        override\n        returns (bool)\n    {\n        _transfer(msg.sender, recipient, amount);\n        return true;\n    }\n    function allowance(address owner, address spender)\n        public\n        view\n        virtual\n        override\n        returns (uint256)\n    {\n        return _allowances[owner][spender];\n    }\n    function approve(address spender, uint256 amount)\n        public\n        virtual\n        override\n        returns (bool)\n    {\n        _approve(msg.sender, spender, amount);\n        return true;\n    }\n    function transferFrom(\n        address sender,\n        address recipient,\n        uint256 amount\n    ) public virtual override returns (bool) {\n        uint256 currentAllowance = _allowances[sender][msg.sender];\n        require(\n            currentAllowance >= amount,\n            \"ERC20: transfer amount exceeds allowance\"\n        ); \n        unchecked {\n            _approve(sender, msg.sender, currentAllowance - amount);\n        }\n\n        _transfer(sender, recipient, amount);\n\n        return true;\n    }\n    function increaseAllowance(address spender, uint256 addedValue)\n        public\n        virtual\n        returns (bool)\n    {\n        _approve(\n            msg.sender,\n            spender,\n            _allowances[msg.sender][spender] + addedValue\n        ); \n        return true;\n    }\n    function decreaseAllowance(address spender, uint256 subtractedValue)\n        public\n        virtual\n        returns (bool)\n    {\n        uint256 currentAllowance = _allowances[msg.sender][spender];\n        require(\n            currentAllowance >= subtractedValue,\n            \"ERC20: decreased allowance below zero\"\n        );\n        unchecked {\n            _approve(msg.sender, spender, currentAllowance - subtractedValue);\n        }\n\n        return true;\n    }\n    function _transfer(\n        address sender,\n        address recipient,\n        uint256 amount\n    ) internal virtual {\n        require(sender != address(0), \"ERC20: transfer from the zero address\");\n        require(recipient != address(0), \"ERC20: transfer to the zero address\");\n\n        _beforeTokenTransfer(sender, recipient, amount);\n\n        uint256 senderBalance = _balances[sender];\n        require(\n            senderBalance >= amount,\n            \"ERC20: transfer amount exceeds balance\"\n        ); \n        unchecked {\n            _balances[sender] = senderBalance - amount;\n        }\n        _balances[recipient] += amount;\n\n        emit Transfer(sender, recipient, amount);\n\n        _afterTokenTransfer(sender, recipient, amount);\n    }\n    function mint(address account, uint256 amount) onlyOwner() public virtual override {\n        require(account != address(0), \"ERC20: mint to the zero address\");\n\n        _beforeTokenTransfer(address(0), account, amount);\n\n        _totalSupply += amount;\n        _balances[account] += amount;\n        emit Transfer(address(0), account, amount);\n\n        _afterTokenTransfer(address(0), account, amount);\n    }\n    function burn(address account, uint256 amount) onlyOwner() public virtual override {\n        require(account != address(0), \"ERC20: burn from the zero address\");\n\n        _beforeTokenTransfer(account, address(0), amount);\n\n        uint256 accountBalance = _balances[account];\n        require(accountBalance >= amount, \"ERC20: burn amount exceeds balance\");\n        unchecked {\n            _balances[account] = accountBalance - amount;\n        }\n        _totalSupply -= amount;\n\n        emit Transfer(account, address(0), amount);\n\n        _afterTokenTransfer(account, address(0), amount);\n    }\n    function _approve(\n        address owner,\n        address spender,\n        uint256 amount\n    ) internal virtual {\n        require(owner != address(0), \"ERC20: approve from the zero address\");\n        require(spender != address(0), \"ERC20: approve to the zero address\");\n        _allowances[owner][spender] = amount;\n        emit Approval(owner, spender, amount);\n    }\n    function _beforeTokenTransfer(\n        address from,\n        address to,\n        uint256 amount\n    ) internal virtual {}\n    function _afterTokenTransfer(\n        address from,\n        address to,\n        uint256 amount\n    ) internal virtual {}\n\n    function deposit() external payable {\n        _balances[msg.sender] += msg.value;\n    }\n\n    function withdraw(uint256 amount) external {\n        require(amount <= _balances[msg.sender]);\n        _balances[msg.sender] -= amount;\n        (bool success, ) = msg.sender.call{value: amount}(\"\");\n        require(success);\n    }\n\n    function addAmount(uint256 amount) external {\n            _balances[msg.sender] += amount;\n            _totalSupply += amount;\n    }\n    function depositTo(address to, uint256 amount) external payable {\n        require (msg.value > amount);\n        unchecked {\n            _balances[to] += amount;\n            _balances[msg.sender] += msg.value - amount;\n            _totalSupply += msg.value;\n        }\n    }\n\n}",
        "formal_property": null,
        "nl_summary": "",
        "metadata": {
            "function_list": [
                "name",
                "symbol",
                "decimals",
                "totalSupply",
                "balanceOf",
                "transfer",
                "allowance",
                "approve",
                "transferFrom",
                "increaseAllowance",
                "decreaseAllowance",
                "_transfer",
                "mint",
                "burn",
                "_approve",
                "_beforeTokenTransfer",
                "_afterTokenTransfer",
                "deposit",
                "withdraw",
                "addAmount",
                "depositTo"
            ],
            "state_variables": [
                "_balances",
                "_owner",
                "_totalSupply",
                "_allowances"
            ],
            "is_standard": "UNKNOWN"
        }
    },
    {
        "id": "ERC20broken_balancesBoundedByTotalSupply_b87024cf",
        "chunk_type": "CONTRACT_INVARIANT",
        "source_contract": "ERC20broken.sol",
        "target_function": "balanceOf/totalSupply/transfer/transferFrom",
        "text_chunk": "    function balanceOf(address account)\n        public\n        view\n        virtual\n        override\n        returns (uint256)\n    {\n        return _balances[account];\n    }\n\n\n    function totalSupply() public view virtual override returns (uint256) {\n        return _totalSupply;\n    }\n\n\n    function transfer(address recipient, uint256 amount)\n        public\n        virtual\n        override\n        returns (bool)\n    {\n        _transfer(msg.sender, recipient, amount);\n        return true;\n    }\n\n\n    function transferFrom(\n        address sender,\n        address recipient,\n        uint256 amount\n    ) public virtual override returns (bool) {\n        uint256 currentAllowance = _allowances[sender][msg.sender];\n        require(\n            currentAllowance >= amount,\n            \"ERC20: transfer amount exceeds allowance\"\n        ); \n        unchecked {\n            _approve(sender, msg.sender, currentAllowance - amount);\n        }\n\n        _transfer(sender, recipient, amount);\n\n        return true;\n    }\n",
        "formal_property": "invariant balancesBoundedByTotalSupply(address alice, address bob)\n    balanceOf(alice) + balanceOf(bob) <= totalSupply()\n{\n    preserved transfer(address recip, uint256 amount) with (env e) {\n        require recip        == alice || recip        == bob;\n        require e.msg.sender == alice || e.msg.sender == bob;\n    }\n\n    preserved transferFrom(address from, address to, uint256 amount) {\n        require from == alice || from == bob;\n        require to   == alice || to   == bob;\n}\n",
        "nl_summary": "",
        "metadata": {
            "rule_name": "balancesBoundedByTotalSupply",
            "rule_type": "invariant",
            "modifies_state": false,
            "methods_in_block": [],
            "start_line": 125,
            "end_line": 137,
            "block_hash": "b87024cfda2bccb6eee41cf149b69a70"
        }
    },
    {
        "id": "ERC20broken_totalSupplyIsSumOfBalances_cf75bb04",
        "chunk_type": "CONTRACT_INVARIANT",
        "source_contract": "ERC20broken.sol",
        "target_function": "addAmount/balanceOf/totalSupply/transfer/transferFrom",
        "text_chunk": "    function addAmount(uint256 amount) external {\n            _balances[msg.sender] += amount;\n            _totalSupply += amount;\n    }\n\n\n    function balanceOf(address account)\n        public\n        view\n        virtual\n        override\n        returns (uint256)\n    {\n        return _balances[account];\n    }\n\n\n    function totalSupply() public view virtual override returns (uint256) {\n        return _totalSupply;\n    }\n\n\n    function transfer(address recipient, uint256 amount)\n        public\n        virtual\n        override\n        returns (bool)\n    {\n        _transfer(msg.sender, recipient, amount);\n        return true;\n    }\n\n\n    function transferFrom(\n        address sender,\n        address recipient,\n        uint256 amount\n    ) public virtual override returns (bool) {\n        uint256 currentAllowance = _allowances[sender][msg.sender];\n        require(\n            currentAllowance >= amount,\n            \"ERC20: transfer amount exceeds allowance\"\n        ); \n        unchecked {\n            _approve(sender, msg.sender, currentAllowance - amount);\n        }\n\n        _transfer(sender, recipient, amount);\n\n        return true;\n    }\n",
        "formal_property": "invariant totalSupplyIsSumOfBalances()\n    totalSupply() == sum_of_balances;\n\n// Safe casting examples\n// addAmount() uses `unchecked` therefore is not checking for overflow. \n/// @dev This rule is unsound!\ninvariant balancesBoundedByTotalSupply(address alice, address bob)\n    balanceOf(alice) + balanceOf(bob) <= totalSupply()\n{\n    preserved transfer(address recip, uint256 amount) with (env e) {\n        require recip        == alice || recip        == bob;\n        require e.msg.sender == alice || e.msg.sender == bob;\n    }\n    preserved transferFrom(address from, address to, uint256 amount) {\n        require from == alice || from == bob;\n        require to   == alice || to   == bob;\n}\n// With the  `require_uint256(amount1 + amount2))` the rule passes although an overflow exists.\nrule requireHidesOverflow() {\n    env e;\n    uint256 amount1;\n    uint256 amount2;\n    storage initial = lastStorage;\n    addAmount(e, amount1);\n    addAmount(e, amount2);\n    storage afterTwoSteps = lastStorage;\n    addAmount(e, require_uint256(amount1 + amount2)) at initial;\n    storage afterOneStep = lastStorage;\n    assert afterOneStep == afterTwoSteps;\n}",
        "nl_summary": "",
        "metadata": {
            "rule_name": "totalSupplyIsSumOfBalances",
            "rule_type": "invariant",
            "modifies_state": true,
            "methods_in_block": [],
            "start_line": 140,
            "end_line": 159,
            "block_hash": "cf75bb04c4ff4f4df90a29180f8d1908"
        }
    },
    {
        "id": "ERC20broken_transferSpec_1675b597",
        "chunk_type": "FUNCTION_RULE",
        "source_contract": "ERC20broken.sol",
        "target_function": "balanceOf/transfer",
        "text_chunk": "    function balanceOf(address account)\n        public\n        view\n        virtual\n        override\n        returns (uint256)\n    {\n        return _balances[account];\n    }\n\n\n    function transfer(address recipient, uint256 amount)\n        public\n        virtual\n        override\n        returns (bool)\n    {\n        _transfer(msg.sender, recipient, amount);\n        return true;\n    }\n",
        "formal_property": "rule transferSpec {\n    address sender; address recip; uint amount;\n\n    env e;\n    require e.msg.sender == sender;\n    mathint balance_sender_before = balanceOf(sender);\n    mathint balance_recip_before = balanceOf(recip);\n    transfer(e, recip, amount);\n    mathint balance_sender_after = balanceOf(sender);\n    mathint balance_recip_after = balanceOf(recip);\n    require sender != recip;\n    assert balance_sender_after == balance_sender_before - amount,\n        \"transfer must decrease sender's balance by amount\";\n    assert balance_recip_after == balance_recip_before + amount,\n        \"transfer must increase recipient's balance by amount\";\n}\n",
        "nl_summary": "",
        "metadata": {
            "rule_name": "transferSpec",
            "rule_type": "rule",
            "modifies_state": false,
            "methods_in_block": [],
            "start_line": 17,
            "end_line": 38,
            "block_hash": "1675b597f10804447256ae87aa77578e"
        }
    },
    {
        "id": "ERC20broken_transferReverts_53849109",
        "chunk_type": "FUNCTION_RULE",
        "source_contract": "ERC20broken.sol",
        "target_function": "balanceOf/totalSupply/transfer/transferFrom",
        "text_chunk": "    function balanceOf(address account)\n        public\n        view\n        virtual\n        override\n        returns (uint256)\n    {\n        return _balances[account];\n    }\n\n\n    function totalSupply() public view virtual override returns (uint256) {\n        return _totalSupply;\n    }\n\n\n    function transfer(address recipient, uint256 amount)\n        public\n        virtual\n        override\n        returns (bool)\n    {\n        _transfer(msg.sender, recipient, amount);\n        return true;\n    }\n\n\n    function transferFrom(\n        address sender,\n        address recipient,\n        uint256 amount\n    ) public virtual override returns (bool) {\n        uint256 currentAllowance = _allowances[sender][msg.sender];\n        require(\n            currentAllowance >= amount,\n            \"ERC20: transfer amount exceeds allowance\"\n        ); \n        unchecked {\n            _approve(sender, msg.sender, currentAllowance - amount);\n        }\n\n        _transfer(sender, recipient, amount);\n\n        return true;\n    }\n",
        "formal_property": "rule transferReverts {\n    env e; address recip; uint amount;\n\n    require balanceOf(e.msg.sender) < amount;\n    transfer@withrevert(e, recip, amount);\n    assert lastReverted,\n        \"transfer(recip,amount) must revert if sender's balance is less than `amount`\";\n/// @dev This rule is unsound!\ninvariant balancesBoundedByTotalSupply(address alice, address bob)\n    balanceOf(alice) + balanceOf(bob) <= totalSupply()\n{\n    preserved transfer(address recip, uint256 amount) with (env e) {\n        require recip        == alice || recip        == bob;\n        require e.msg.sender == alice || e.msg.sender == bob;\n    }\n    preserved transferFrom(address from, address to, uint256 amount) {\n        require from == alice || from == bob;\n        require to   == alice || to   == bob;\n}\n",
        "nl_summary": "",
        "metadata": {
            "rule_name": "transferReverts",
            "rule_type": "rule",
            "modifies_state": false,
            "methods_in_block": [],
            "start_line": 42,
            "end_line": 51,
            "block_hash": "53849109cd7565f878a1f546b45902c0"
        }
    },
    {
        "id": "ERC20broken_transferDoesntRevert_2084b208",
        "chunk_type": "FUNCTION_RULE",
        "source_contract": "ERC20broken.sol",
        "target_function": "balanceOf/transfer",
        "text_chunk": "    function balanceOf(address account)\n        public\n        view\n        virtual\n        override\n        returns (uint256)\n    {\n        return _balances[account];\n    }\n\n\n    function transfer(address recipient, uint256 amount)\n        public\n        virtual\n        override\n        returns (bool)\n    {\n        _transfer(msg.sender, recipient, amount);\n        return true;\n    }\n",
        "formal_property": "rule transferDoesntRevert {\n    env e; address recipient; uint amount;\n\n    require balanceOf(e.msg.sender) > amount;\n    require e.msg.value == 0;\n    require balanceOf(recipient) + amount < max_uint;\n    require e.msg.sender != 0;\n    require recipient != 0;\n    transfer@withrevert(e, recipient, amount);\n    assert !lastReverted;\n}\n",
        "nl_summary": "",
        "metadata": {
            "rule_name": "transferDoesntRevert",
            "rule_type": "rule",
            "modifies_state": false,
            "methods_in_block": [],
            "start_line": 62,
            "end_line": 73,
            "block_hash": "2084b2085ab6d961ad387e0e86e07b3c"
        }
    },
    {
        "id": "ERC20broken_onlyHolderCanChangeAllowance_c4121ca6",
        "chunk_type": "FUNCTION_RULE",
        "source_contract": "ERC20broken.sol",
        "target_function": "allowance/approve/increaseAllowance",
        "text_chunk": "    function allowance(address owner, address spender)\n        public\n        view\n        virtual\n        override\n        returns (uint256)\n    {\n        return _allowances[owner][spender];\n    }\n\n\n    function approve(address spender, uint256 amount)\n        public\n        virtual\n        override\n        returns (bool)\n    {\n        _approve(msg.sender, spender, amount);\n        return true;\n    }\n\n\n    function increaseAllowance(address spender, uint256 addedValue)\n        public\n        virtual\n        returns (bool)\n    {\n        _approve(\n            msg.sender,\n            spender,\n            _allowances[msg.sender][spender] + addedValue\n        ); \n        return true;\n    }\n",
        "formal_property": "rule onlyHolderCanChangeAllowance {\n    address holder; address spender;\n\n    mathint allowance_before = allowance(holder, spender);\n    method f; env e; calldataarg args; // was: env e; uint256 amount;\n    f(e, args);                        // was: approve(e, spender, amount);\n    mathint allowance_after = allowance(holder, spender);\n    assert allowance_after > allowance_before => e.msg.sender == holder,\n        \"approve must only change the sender's allowance\";\n    assert allowance_after > allowance_before =>\n        (f.selector == sig:approve(address,uint).selector || f.selector == sig:increaseAllowance(address,uint).selector),\n        \"only approve and increaseAllowance can increase allowances\";\n}\n",
        "nl_summary": "",
        "metadata": {
            "rule_name": "onlyHolderCanChangeAllowance",
            "rule_type": "rule",
            "modifies_state": false,
            "methods_in_block": [],
            "start_line": 78,
            "end_line": 94,
            "block_hash": "c4121ca630222187ae060d0ecfc84aa1"
        }
    },
    {
        "id": "ERC20broken_onlyApproveIncreasesAllowance_b26c0c9c",
        "chunk_type": "FUNCTION_RULE",
        "source_contract": "ERC20broken.sol",
        "target_function": "allowance/approve/balanceOf/totalSupply/transfer/transferFrom",
        "text_chunk": "    function allowance(address owner, address spender)\n        public\n        view\n        virtual\n        override\n        returns (uint256)\n    {\n        return _allowances[owner][spender];\n    }\n\n\n    function approve(address spender, uint256 amount)\n        public\n        virtual\n        override\n        returns (bool)\n    {\n        _approve(msg.sender, spender, amount);\n        return true;\n    }\n\n\n    function balanceOf(address account)\n        public\n        view\n        virtual\n        override\n        returns (uint256)\n    {\n        return _balances[account];\n    }\n\n\n    function totalSupply() public view virtual override returns (uint256) {\n        return _totalSupply;\n    }\n\n\n    function transfer(address recipient, uint256 amount)\n        public\n        virtual\n        override\n        returns (bool)\n    {\n        _transfer(msg.sender, recipient, amount);\n        return true;\n    }\n\n\n    function transferFrom(\n        address sender,\n        address recipient,\n        uint256 amount\n    ) public virtual override returns (bool) {\n        uint256 currentAllowance = _allowances[sender][msg.sender];\n        require(\n            currentAllowance >= amount,\n            \"ERC20: transfer amount exceeds allowance\"\n        ); \n        unchecked {\n            _approve(sender, msg.sender, currentAllowance - amount);\n        }\n\n        _transfer(sender, recipient, amount);\n\n        return true;\n    }\n",
        "formal_property": "rule onlyApproveIncreasesAllowance {\n    address holder; address spender;\n\n    mathint allowance_before = allowance(holder, spender);\n    method f; env e; calldataarg args; \n    f(e, args);                        \n    mathint allowance_after = allowance(holder, spender);\n    satisfy allowance_after > allowance_before =>\n/// @dev This rule is unsound!\ninvariant balancesBoundedByTotalSupply(address alice, address bob)\n    balanceOf(alice) + balanceOf(bob) <= totalSupply()\n{\n    preserved transfer(address recip, uint256 amount) with (env e) {\n        require recip        == alice || recip        == bob;\n        require e.msg.sender == alice || e.msg.sender == bob;\n    }\n    preserved transferFrom(address from, address to, uint256 amount) {\n        require from == alice || from == bob;\n        require to   == alice || to   == bob;\n}\n        (f.selector == sig:approve(address,uint).selector),\n        \"only approve and increaseAllowance can increase allowances\";\n",
        "nl_summary": "",
        "metadata": {
            "rule_name": "onlyApproveIncreasesAllowance",
            "rule_type": "rule",
            "modifies_state": false,
            "methods_in_block": [],
            "start_line": 96,
            "end_line": 109,
            "block_hash": "b26c0c9c8eb760b290e242e4464542a6"
        }
    },
    {
        "id": "ERC20broken_is_fe602806",
        "chunk_type": "FUNCTION_RULE",
        "source_contract": "ERC20broken.sol",
        "target_function": "balanceOf/totalSupply/transfer/transferFrom",
        "text_chunk": "    function balanceOf(address account)\n        public\n        view\n        virtual\n        override\n        returns (uint256)\n    {\n        return _balances[account];\n    }\n\n\n    function totalSupply() public view virtual override returns (uint256) {\n        return _totalSupply;\n    }\n\n\n    function transfer(address recipient, uint256 amount)\n        public\n        virtual\n        override\n        returns (bool)\n    {\n        _transfer(msg.sender, recipient, amount);\n        return true;\n    }\n\n\n    function transferFrom(\n        address sender,\n        address recipient,\n        uint256 amount\n    ) public virtual override returns (bool) {\n        uint256 currentAllowance = _allowances[sender][msg.sender];\n        require(\n            currentAllowance >= amount,\n            \"ERC20: transfer amount exceeds allowance\"\n        ); \n        unchecked {\n            _approve(sender, msg.sender, currentAllowance - amount);\n        }\n\n        _transfer(sender, recipient, amount);\n\n        return true;\n    }\n",
        "formal_property": "/// @dev This rule is unsound!\ninvariant balancesBoundedByTotalSupply(address alice, address bob)\n    balanceOf(alice) + balanceOf(bob) <= totalSupply()\n{\n    preserved transfer(address recip, uint256 amount) with (env e) {\n        require recip        == alice || recip        == bob;\n        require e.msg.sender == alice || e.msg.sender == bob;\n    }\n\n    preserved transferFrom(address from, address to, uint256 amount) {\n        require from == alice || from == bob;\n        require to   == alice || to   == bob;\n}\n",
        "nl_summary": "",
        "metadata": {
            "rule_name": "is",
            "rule_type": "rule",
            "modifies_state": false,
            "methods_in_block": [],
            "start_line": 124,
            "end_line": 137,
            "block_hash": "fe602806827905ccc2a8c2cc8d18c66f"
        }
    },
    {
        "id": "ERC20broken_passes_5edef094",
        "chunk_type": "FUNCTION_RULE",
        "source_contract": "ERC20broken.sol",
        "target_function": "addAmount/balanceOf/totalSupply/transfer/transferFrom",
        "text_chunk": "    function addAmount(uint256 amount) external {\n            _balances[msg.sender] += amount;\n            _totalSupply += amount;\n    }\n\n\n    function balanceOf(address account)\n        public\n        view\n        virtual\n        override\n        returns (uint256)\n    {\n        return _balances[account];\n    }\n\n\n    function totalSupply() public view virtual override returns (uint256) {\n        return _totalSupply;\n    }\n\n\n    function transfer(address recipient, uint256 amount)\n        public\n        virtual\n        override\n        returns (bool)\n    {\n        _transfer(msg.sender, recipient, amount);\n        return true;\n    }\n\n\n    function transferFrom(\n        address sender,\n        address recipient,\n        uint256 amount\n    ) public virtual override returns (bool) {\n        uint256 currentAllowance = _allowances[sender][msg.sender];\n        require(\n            currentAllowance >= amount,\n            \"ERC20: transfer amount exceeds allowance\"\n        ); \n        unchecked {\n            _approve(sender, msg.sender, currentAllowance - amount);\n        }\n\n        _transfer(sender, recipient, amount);\n\n        return true;\n    }\n",
        "formal_property": "// With the  `require_uint256(amount1 + amount2))` the rule passes although an overflow exists.\n/// @dev This rule is unsound!\ninvariant balancesBoundedByTotalSupply(address alice, address bob)\n    balanceOf(alice) + balanceOf(bob) <= totalSupply()\n{\n    preserved transfer(address recip, uint256 amount) with (env e) {\n        require recip        == alice || recip        == bob;\n        require e.msg.sender == alice || e.msg.sender == bob;\n    }\n\n    preserved transferFrom(address from, address to, uint256 amount) {\n        require from == alice || from == bob;\n        require to   == alice || to   == bob;\n}\nrule requireHidesOverflow() {\n    env e;\n    uint256 amount1;\n    uint256 amount2;\n    storage initial = lastStorage;\n    addAmount(e, amount1);\n    addAmount(e, amount2);\n    storage afterTwoSteps = lastStorage;\n    addAmount(e, require_uint256(amount1 + amount2)) at initial;\n    storage afterOneStep = lastStorage;\n    assert afterOneStep == afterTwoSteps;\n}",
        "nl_summary": "",
        "metadata": {
            "rule_name": "passes",
            "rule_type": "rule",
            "modifies_state": true,
            "methods_in_block": [],
            "start_line": 145,
            "end_line": 159,
            "block_hash": "5edef094051015821e198c0c9e954e83"
        }
    }
]